{
  "schemaVersion": 1,
  "manifestVersion": "2026.05.24-1",
  "featureFlags": {
    "premiumTTSEnabled": true
  },
  "sharedBases": [
    {
      "identifier": "kokoro-en-base-v1.1",
      "engine": "kokoro",
      "engineVersion": "1.0",
      "downloadSizeBytes": 351748854,
      "cdnURL": "https://github.com/genericgroup/articleq-voice-models/releases/download/base-en-v1.1/kokoro-en-base-v1.1.aar",
      "sha256": "12b17014d042b44912937433b4d87f8c20e075a205fb7d9a653edade5966aba1"
    }
  ],
  "voices": [
    {
      "id": "kokoro-en-bf-emma",
      "displayName": "Emma",
      "locale": "en-GB",
      "gender": "female",
      "style": "narrator",
      "engine": "kokoro",
      "engineVersion": "1.0",
      "sharedBaseId": "kokoro-en-base-v1.1",
      "kokoroSpeakerId": 21,
      "sampleSentence": "Good morning. Today's news brings updates from across the world, with new developments in technology, science, and culture that may interest you."
    }
  ]
}
